[
    {
      "task": {
        "name": "Step 1: Land Inspection",
        "subtask": [
          {
            "name": "Choose Type of Land",
            "condition": {
              "property": "land.type",
              "cases": [
                {
                  "value": "Raw",
                  "subtask": {
                    "name": "Raw Land",
                    "subtask": [
                      {
                        "name": "Remove Unwanted Objects (Raw Land)",
                        "subtask": [
                          {
                            "name": "Provision of water & electricity supply (Raw Land)",
                            "subtask": []
                          },
                          {
                            "name": "Initiate Soil inspection (Raw Land)",
                            "subtask": []
                          }
                        ]
                      }
                    ]
                  }
                },
                {
                  "value": "Constructed",
                  "subtask": {
                    "name": "Constructed Land",
                    "subtask": [
                      {
                        "name": "Initiate Demolition",
                        "subtask": [
                          {
                            "name": "Remove Unwanted Objects (Constructed Land)",
                            "subtask": [
                              {
                                "name": "Provision of water & electricity supply (Constructed Land)",
                                "subtask": []
                              },
                              {
                                "name": "Initiate Soil inspection (Constructed Land)",
                                "subtask": []
                              }
                            ]
                          }
                        ]
                      }
                    ]
                  }
                },
                {
                  "value": "Water",
                  "subtask": {
                    "name": "Water-Filled Land",
                    "subtask": [
                      {
                        "name": "Drain Water",
                        "subtask": [
                          {
                            "name": "Remove Unwanted Objects (Water-Filled Land)",
                            "subtask": [
                              {
                                "name": "Provision of water & electricity supply (Water-Filled Land)",
                                "subtask": []
                              },
                              {
                                "name": "Initiate Soil inspection (Water-Filled Land)",
                                "subtask": []
                              }
                            ]
                          }
                        ]
                      }
                    ]
                  }
                }
              ],
              "defaultSubtask": {
                "name": "Unknown Land Type",
                "subtask": []
              }
            }
          }
        ]
      }
    },
    {
      "task": {
        "name": "Proceed to Step 2 (Constructed Land)",
        "subtask": [
            {
              "task": {
                "name": "Piling",
                "subtask": [
                  {
                    "name": "Marking Centerline",
                    "subtask": []
                  },
                  {
                    "name": "Pit Excavation",
                    "subtask": []
                  },
                  {
                    "name": "Steel Cage Insertion",
                    "subtask": []
                  },
                  {
                    "name": "Boring",
                    "subtask": []
                  }
                ]
              }
            },
            {
              "task": {
                "name": "Excavation",
                "subtask": []
              }
            },
            {
              "task": {
                "name": "Foundation Consolidation",
                "subtask": []
              }
            },
            {
              "task": {
                "name": "Footing",
                "subtask": [
                  {
                    "name": "Upload # of Columns",
                    "subtask": []
                  },
                  {
                    "name": "Upload Column Marking Image",
                    "subtask": []
                  },
                  {
                    "name": "Column Position Marking",
                    "subtask": []
                  },
                  {
                    "name": "Spacing Mesh Deployment",
                    "subtask": []
                  },
                  {
                    "name": "Formwork / Reinforcement",
                    "subtask": []
                  },
                  {
                    "name": "RCC of Footing",
                    "subtask": []
                  },
                  {
                    "name": "Remove Air Bubbles",
                    "subtask": []
                  },
                  {
                    "name": "Remove Formwork / Reinforcement",
                    "subtask": []
                  }
                ]
              }
            },
            {
              "task": {
                "name": "Neck Column",
                "subtask": [
                  {
                    "name": "Reinforcement / Formwork",
                    "subtask": []
                  },
                  {
                    "name": "RCC Pouring",
                    "subtask": []
                  },
                  {
                    "name": "Shuttering / Form Removal",
                    "subtask": []
                  }
                ]
              }
            },
            {
              "task": {
                "name": "Foundation Wall",
                "subtask": []
              }
            },
            {
              "task": {
                "name": "Backfilling of Land",
                "subtask": []
              }
            },
            {
              "task": {
                "name": "Tie Beam",
                "subtask": [
                  {
                    "name": "PCC Bed",
                    "subtask": []
                  },
                  {
                    "name": "Steel Reinforcement",
                    "subtask": []
                  },
                  {
                    "name": "Formwork",
                    "subtask": []
                  }
                ]
              }
            },
            {
                "task": {
                  "name": "Walls Work",
                  "subtask": [
                    {
                      "name": "Wall Marking (Ranged According to Map)",
                      "subtask": []
                    },
                    {
                      "name": "Column Erection",
                      "subtask": [
                        {
                          "name": "Ring Position Verification of Column Number",
                          "subtask": []
                        }
                      ]
                    },
                    {
                      "name": "Column Casting",
                      "subtask": [
                        {
                          "name": "Reinforcement",
                          "subtask": []
                        },
                        {
                          "name": "Mixing Ratio",
                          "subtask": []
                        },
                        {
                          "name": "RCC",
                          "subtask": []
                        },
                        {
                          "name": "Air Bubble Removal",
                          "subtask": []
                        },
                        {
                          "name": "Removal of Reinforcement",
                          "subtask": []
                        },
                        {
                          "name": "Height of Column Verification",
                          "subtask": []
                        }
                      ]
                    },
                    {
                      "name": "5 ft Wall Work",
                      "subtask": [
                        {
                          "name": "Mixing Ratio 6:1 Subtask",
                          "subtask": []
                        }
                      ]
                    },
                    {
                      "name": "Above 5 ft Wall",
                      "subtask": []
                    },
                    {
                      "name": "Chajja / Frame Work",
                      "subtask": []
                    },
                    {
                      "name": "Staircase",
                      "subtask": [
                        {
                          "name": "Shuttering",
                          "subtask": []
                        },
                        {
                          "name": "RCC",
                          "subtask": []
                        },
                        {
                          "name": "Air Bubble Removal",
                          "subtask": []
                        },
                        {
                          "name": "Removal of Shuttering",
                          "subtask": []
                        }
                      ]
                    },
                    {
                      "name": "Shuttering",
                      "subtask": []
                    },
                    {
                      "name": "Pre-Slab Casting",
                      "subtask": [
                        {
                          "name": "Steel Staging",
                          "subtask": []
                        },
                        {
                          "name": "Plumber Fitting",
                          "subtask": []
                        },
                        {
                          "name": "Electrical Fitting",
                          "subtask": []
                        }
                      ]
                    },
                    {
                      "name": "Slab Casting",
                      "subtask": [
                        {
                          "name": "Mixing",
                          "subtask": []
                        },
                        {
                            "name": "Vibration",
                            "subtask": []
                        },
                        {
                          "name": "Lenter Presence",
                          "subtask": []
                        }
                      ]
                    },
                    {
                        "task": {
                          "name": "Deshutting",
                          "subtask": []
                        }
                    },
                    {
                        "task": {
                          "name": "Step 3: Walls, Columns & Slab Work",
                          "subtask": [
                            {
                              "name": "Wall marking (Ranged according to map)",
                              "subtask": []
                            },
                            {
                              "name": "Column erecting",
                              "subtask": [
                                {
                                  "name": "Ring position verification w.r.t column number",
                                  "subtask": []
                                }
                              ]
                            },
                            {
                              "name": "Column casting",
                              "subtask": [
                                {
                                  "name": "Curing",
                                  "subtask": []
                                },
                                {
                                  "name": "Reinforcement",
                                  "subtask": []
                                },
                                {
                                  "name": "Mixing ratio",
                                  "subtask": []
                                },
                                {
                                  "name": "RCC",
                                  "subtask": []
                                },
                                {
                                  "name": "Air bubble removal",
                                  "subtask": []
                                },
                                {
                                  "name": "Removal of Reinforcement",
                                  "subtask": []
                                }
                              ]
                            },
                            {
                              "name": "5 feet wall work",
                              "subtask": [
                                {
                                  "name": "Curing",
                                  "subtask": []
                                },
                                {
                                  "name": "Mixing ratio (6:1) subtask",
                                  "subtask": []
                                }
                              ]
                            },
                            {
                              "name": "Above 5 foot wall",
                              "subtask": []
                            },
                            {
                              "name": "Choukhat Frame work",
                              "subtask": []
                            },
                            {
                              "name": "Staircase",
                              "subtask": [
                                {
                                  "name": "Shuttering",
                                  "subtask": []
                                },
                                {
                                  "name": "RCC",
                                  "subtask": []
                                },
                                {
                                  "name": "Air Bubble removal",
                                  "subtask": []
                                },
                                {
                                  "name": "Removal of shuttering",
                                  "subtask": []
                                }
                              ]
                            },
                            {
                              "name": "Shuttering",
                              "subtask": []
                            },
                            {
                              "name": "Pre Slab casting",
                              "subtask": [
                                {
                                  "name": "Steel binding",
                                  "subtask": []
                                },
                                {
                                  "name": "Plumber fitting",
                                  "subtask": []
                                },
                                {
                                  "name": "Electrical fitting",
                                  "subtask": []
                                }
                              ]
                            },
                            {
                              "name": "Slab casting",
                              "subtask": [
                                {
                                  "name": "Mixing",
                                  "subtask": []
                                },
                                {
                                  "name": "Vibration",
                                  "subtask": []
                                },
                                {
                                  "name": "Lenter presence",
                                  "subtask": []
                                }
                              ]
                            }
                          ]
                        }
                    },
                    {
                        "task": {
                          "name": "Step 4: Floor Work & Interiors",
                          "subtask": [
                            {
                              "name": "Floor Work",
                              "subtask": [
                                {
                                  "name": "Electrical Points",
                                  "subtask": []
                                },
                                {
                                  "name": "Plumbing Work",
                                  "subtask": []
                                },
                                {
                                  "name": "Wall Plaster",
                                  "subtask": []
                                },
                                {
                                  "name": "Floor Levelling",
                                  "subtask": []
                                },
                                {
                                  "name": "Flooring",
                                  "subtask": [
                                    {
                                      "name": "Marble Tiles",
                                      "subtask": []
                                    }
                                  ]
                                },
                                {
                                  "name": "False Ceiling",
                                  "subtask": [
                                    {
                                      "name": "Framing",
                                      "subtask": [
                                        {
                                          "name": "Lighting",
                                          "subtask": [
                                            {
                                              "name": "POP",
                                              "subtask": []
                                            }
                                          ]
                                        }
                                      ]
                                    }
                                  ]
                                }
                              ]
                            },
                            {
                              "name": "Electrical Wiring",
                              "subtask": []
                            },
                            {
                              "name": "Carpenter",
                              "subtask": []
                            },
                            {
                              "name": "Paint Work",
                              "subtask": []
                            },
                            {
                              "name": "Finishing",
                              "subtask": []
                            },
                            {
                              "name": "Bath Works",
                              "subtask": []
                            },
                            {
                              "name": "Interior Work",
                              "subtask": []
                            },
                            {
                                "name": "Upload Progress Image",
                                "subtask": []
                            },
                            {
                                "name": "Upload Final Image",
                                "subtask": []
                            }
                          ]
                        }
                    }
                  ]
                }
            },
            {
                "task": {
                  "name": "Deshutting",
                  "subtask": [
                    {
                      "name": "Walls Work",
                      "subtask": [
                        {
                          "name": "Wall marking (Ranged according to map)",
                          "subtask": []
                        },
                        {
                          "name": "Column erecting",
                          "subtask": [
                            {
                              "name": "Ring position verification w.r.t column number",
                              "subtask": []
                            }
                          ]
                        },
                        {
                          "name": "Column casting",
                          "subtask": [
                            {
                              "name": "Curing",
                              "subtask": []
                            },
                            {
                              "name": "Reinforcement",
                              "subtask": []
                            },
                            {
                              "name": "Mixing ratio",
                              "subtask": []
                            },
                            {
                              "name": "RCC",
                              "subtask": []
                            },
                            {
                              "name": "Air bubble removal",
                              "subtask": []
                            },
                            {
                              "name": "Removal of Reinforcement",
                              "subtask": []
                            }
                          ]
                        },
                        {
                          "name": "5 feet wall work",
                          "subtask": [
                            {
                              "name": "Curing",
                              "subtask": []
                            },
                            {
                              "name": "Mixing ratio (6:1) subtask",
                              "subtask": []
                            }
                          ]
                        },
                        {
                          "name": "Above 5 foot wall",
                          "subtask": []
                        },
                        {
                          "name": "Choukhat Frame work",
                          "subtask": []
                        },
                        {
                          "name": "Staircase",
                          "subtask": [
                            {
                              "name": "Shuttering",
                              "subtask": []
                            },
                            {
                              "name": "RCC",
                              "subtask": []
                            },
                            {
                              "name": "Air bubble removal",
                              "subtask": []
                            },
                            {
                              "name": "Removal of shuttering",
                              "subtask": []
                            }
                          ]
                        },
                        {
                          "name": "Shuttering",
                          "subtask": []
                        },
                        {
                          "name": "Pre Slab casting",
                          "subtask": [
                            {
                              "name": "Steel binding",
                              "subtask": []
                            },
                            {
                              "name": "Plumber fitting",
                              "subtask": []
                            },
                            {
                              "name": "Electrical fitting",
                              "subtask": []
                            }
                          ]
                        },
                        {
                          "name": "Slab casting",
                          "subtask": [
                            {
                              "name": "Mixing",
                              "subtask": []
                            },
                            {
                              "name": "Vibration",
                              "subtask": []
                            },
                            {
                              "name": "Lenter presence",
                              "subtask": []
                            }
                          ]
                        },
                        {
                          "name": "De Shuttering",
                          "subtask": []
                        },
                        {
                          "name": "Parapet work",
                          "subtask": []
                        },
                        {
                          "name": "Front elevation",
                          "subtask": [
                            {
                              "name": "Outer plaster",
                              "subtask": []
                            },
                            {
                              "name": "Front tiles",
                              "subtask": []
                            },
                            {
                              "name": "Balcony work",
                              "subtask": []
                            },
                            {
                              "name": "Railing",
                              "subtask": []
                            }
                          ]
                        },
                        {
                          "name": "Ground Floor flooring",
                          "subtask": [
                            {
                              "name": "Inside",
                              "subtask": []
                            }
                          ]
                        }
                      ]
                    },
                    {
                      "name": "Floor Work & Interiors",
                      "subtask": [
                        {
                          "name": "Floor Work",
                          "subtask": [
                            {
                              "name": "Electrical Points",
                              "subtask": []
                            },
                            {
                              "name": "Plumbing Work",
                              "subtask": []
                            },
                            {
                              "name": "Wall Plaster",
                              "subtask": []
                            },
                            {
                              "name": "Floor Levelling",
                              "subtask": []
                            },
                            {
                              "name": "Flooring",
                              "subtask": [
                                {
                                  "name": "Marble Tiles",
                                  "subtask": []
                                }
                              ]
                            },
                            {
                              "name": "False Ceiling",
                              "subtask": [
                                {
                                  "name": "Framing",
                                  "subtask": [
                                    {
                                      "name": "Lighting",
                                      "subtask": [
                                        {
                                          "name": "POP",
                                          "subtask": []
                                        }
                                      ]
                                    }
                                  ]
                                }
                              ]
                            }
                          ]
                        },
                        {
                          "name": "Electrical Wiring",
                          "subtask": []
                        },
                        {
                          "name": "Carpenter",
                          "subtask": []
                        },
                        {
                          "name": "Paint Work",
                          "subtask": []
                        },
                        {
                          "name": "Finishing",
                          "subtask": []
                        },
                        {
                          "name": "Bath Works",
                          "subtask": []
                        },
                        {
                          "name": "Interior Work",
                          "subtask": [
                            {
                              "name": "Upload Progress Image",
                              "subtask": [
                                {
                                  "name": "Upload Final Proof",
                                  "subtask": []
                                }
                              ]
                            }
                          ]
                        }
                      ]
                    }
                  ]
                }
            }           
          ]          
      }
    }
  ]





